qycli/__init__.py
qycli/command.py
qycli/globals.py
qycli/httpcli.py
qycli/main.py
qycli/parser.py
qycli-0.15.dist-info/METADATA
qycli-0.15.dist-info/RECORD
qycli-0.15.dist-info/WHEEL
qycli-0.15.dist-info/entry_points.txt
qycli-0.15.dist-info/top_level.txt
test/__init__.py
test/main.py
