Metadata-Version: 2.1
Name: qycli
Version: 0.15
Summary: qycli command line
Home-page: http://blog.csdn.net/naralv/
Author: lijun
Author-email: naralv@126.com
License: MIT
Platform: UNKNOWN
Classifier: Programming Language :: Python :: 3
Classifier: License :: OSI Approved :: MIT License
Classifier: Operating System :: OS Independent
Requires-Dist: requests
